{
  "rootId": 19206259,
  "currentNodeId": 19206259,
  "nodes": {
    "19206259": {
      "id": 19206259,
      "state": {
        "key": "root",
        "pgn": "root",
        "whitesTurn": true,
        "squares": {
          "a1": "wr1",
          "b1": "wn1",
          "c1": "wb1",
          "d1": "wq1",
          "e1": "wk1",
          "f1": "wb2",
          "g1": "wn2",
          "h1": "wr2",
          "a2": "wp1",
          "b2": "wp2",
          "c2": "wp3",
          "d2": "wp4",
          "e2": "wp5",
          "f2": "wp6",
          "g2": "wp7",
          "h2": "wp8",
          "a7": "bp1",
          "b7": "bp2",
          "c7": "bp3",
          "d7": "bp4",
          "e7": "bp5",
          "f7": "bp6",
          "g7": "bp7",
          "h7": "bp8",
          "a8": "br1",
          "b8": "bn1",
          "c8": "bb1",
          "d8": "bq1",
          "e8": "bk1",
          "f8": "bb2",
          "g8": "bn2",
          "h8": "br2"
        },
        "moves": [],
        "comments": [
          "Scotch Game"
        ]
      },
      "parentId": 0,
      "childIds": [
        614154010
      ],
      "childIdx": 0
    },
    "244527714": {
      "id": 244527714,
      "state": {
        "key": "g1f3",
        "pgn": "Nf3",
        "whitesTurn": false,
        "squares": {
          "a1": "wr1",
          "b1": "wn1",
          "c1": "wb1",
          "d1": "wq1",
          "e1": "wk1",
          "f1": "wb2",
          "h1": "wr2",
          "a2": "wp1",
          "b2": "wp2",
          "c2": "wp3",
          "d2": "wp4",
          "f2": "wp6",
          "g2": "wp7",
          "h2": "wp8",
          "a7": "bp1",
          "b7": "bp2",
          "c7": "bp3",
          "d7": "bp4",
          "f7": "bp6",
          "g7": "bp7",
          "h7": "bp8",
          "a8": "br1",
          "b8": "bn1",
          "c8": "bb1",
          "d8": "bq1",
          "e8": "bk1",
          "f8": "bb2",
          "g8": "bn2",
          "h8": "br2",
          "e4": "wp5",
          "e5": "bp5",
          "f3": "wn2"
        },
        "moves": [
          [
            "e2",
            "e4"
          ],
          [
            "e7",
            "e5"
          ],
          [
            "g1",
            "f3"
          ]
        ],
        "marks": {
          "yellow": [
            "g1",
            "f3"
          ]
        }
      },
      "parentId": 1877669921,
      "childIds": [
        1156584507
      ],
      "childIdx": 0
    },
    "262827214": {
      "id": 262827214,
      "state": {
        "key": "f6g6",
        "pgn": "Qg6",
        "whitesTurn": true,
        "squares": {
          "a1": "wr1",
          "b1": "wn1",
          "d1": "wq1",
          "e1": "wk1",
          "f1": "wb2",
          "h1": "wr2",
          "a2": "wp1",
          "b2": "wp2",
          "f2": "wp6",
          "g2": "wp7",
          "h2": "wp8",
          "a7": "bp1",
          "b7": "bp2",
          "c7": "bp3",
          "d7": "bp4",
          "f7": "bp6",
          "g7": "bp7",
          "h7": "bp8",
          "a8": "br1",
          "c8": "bb1",
          "e8": "bk1",
          "g8": "bn2",
          "h8": "br2",
          "e4": "wp5",
          "c6": "bn1",
          "d4": "wn2",
          "c5": "bb2",
          "e3": "wb1",
          "c3": "wp3",
          "g6": "bq1"
        },
        "moves": [
          [
            "e2",
            "e4"
          ],
          [
            "e7",
            "e5"
          ],
          [
            "g1",
            "f3"
          ],
          [
            "b8",
            "c6"
          ],
          [
            "d2",
            "d4"
          ],
          [
            "e5",
            "d4"
          ],
          [
            "f3",
            "d4"
          ],
          [
            "f8",
            "c5"
          ],
          [
            "c1",
            "e3"
          ],
          [
            "d8",
            "f6"
          ],
          [
            "c2",
            "c3"
          ],
          [
            "f6",
            "g6"
          ]
        ],
        "comments": [
          "Scotch Game, Classical Variation, Millennium Variation"
        ],
        "marks": {
          "yellow": [
            "f6",
            "g6"
          ]
        }
      },
      "parentId": 1116250706,
      "childIds": [],
      "childIdx": -1
    },
    "262858866": {
      "id": 262858866,
      "state": {
        "key": "g8e7",
        "pgn": "ge7",
        "whitesTurn": true,
        "squares": {
          "a1": "wr1",
          "b1": "wn1",
          "d1": "wq1",
          "e1": "wk1",
          "f1": "wb2",
          "h1": "wr2",
          "a2": "wp1",
          "b2": "wp2",
          "f2": "wp6",
          "g2": "wp7",
          "h2": "wp8",
          "a7": "bp1",
          "b7": "bp2",
          "c7": "bp3",
          "d7": "bp4",
          "f7": "bp6",
          "g7": "bp7",
          "h7": "bp8",
          "a8": "br1",
          "c8": "bb1",
          "e8": "bk1",
          "h8": "br2",
          "e4": "wp5",
          "c6": "bn1",
          "d4": "wn2",
          "c5": "bb2",
          "e3": "wb1",
          "f6": "bq1",
          "c3": "wp3",
          "e7": "bn2"
        },
        "moves": [
          [
            "e2",
            "e4"
          ],
          [
            "e7",
            "e5"
          ],
          [
            "g1",
            "f3"
          ],
          [
            "b8",
            "c6"
          ],
          [
            "d2",
            "d4"
          ],
          [
            "e5",
            "d4"
          ],
          [
            "f3",
            "d4"
          ],
          [
            "f8",
            "c5"
          ],
          [
            "c1",
            "e3"
          ],
          [
            "d8",
            "f6"
          ],
          [
            "c2",
            "c3"
          ],
          [
            "g8",
            "e7"
          ]
        ],
        "marks": {
          "yellow": [
            "g8",
            "e7"
          ]
        }
      },
      "parentId": 1116250706,
      "childIds": [
        1724905953,
        1724903101
      ],
      "childIdx": 0
    },
    "614154010": {
      "id": 614154010,
      "state": {
        "key": "e2e4",
        "pgn": "e4",
        "whitesTurn": false,
        "squares": {
          "a1": "wr1",
          "b1": "wn1",
          "c1": "wb1",
          "d1": "wq1",
          "e1": "wk1",
          "f1": "wb2",
          "g1": "wn2",
          "h1": "wr2",
          "a2": "wp1",
          "b2": "wp2",
          "c2": "wp3",
          "d2": "wp4",
          "f2": "wp6",
          "g2": "wp7",
          "h2": "wp8",
          "a7": "bp1",
          "b7": "bp2",
          "c7": "bp3",
          "d7": "bp4",
          "e7": "bp5",
          "f7": "bp6",
          "g7": "bp7",
          "h7": "bp8",
          "a8": "br1",
          "b8": "bn1",
          "c8": "bb1",
          "d8": "bq1",
          "e8": "bk1",
          "f8": "bb2",
          "g8": "bn2",
          "h8": "br2",
          "e4": "wp5"
        },
        "moves": [
          [
            "e2",
            "e4"
          ]
        ],
        "marks": {
          "yellow": [
            "e2",
            "e4"
          ]
        }
      },
      "parentId": 19206259,
      "childIds": [
        1877669921
      ],
      "childIdx": 0
    },
    "728637340": {
      "id": 728637340,
      "state": {
        "key": "f8c5",
        "pgn": "Bc5",
        "whitesTurn": true,
        "squares": {
          "a1": "wr1",
          "b1": "wn1",
          "c1": "wb1",
          "d1": "wq1",
          "e1": "wk1",
          "h1": "wr2",
          "a2": "wp1",
          "b2": "wp2",
          "c2": "wp3",
          "f2": "wp6",
          "g2": "wp7",
          "h2": "wp8",
          "a7": "bp1",
          "b7": "bp2",
          "c7": "bp3",
          "d7": "bp4",
          "f7": "bp6",
          "g7": "bp7",
          "h7": "bp8",
          "a8": "br1",
          "c8": "bb1",
          "d8": "bq1",
          "e8": "bk1",
          "g8": "bn2",
          "h8": "br2",
          "e4": "wp5",
          "f3": "wn2",
          "c6": "bn1",
          "d4": "bp5",
          "c4": "wb2",
          "c5": "bb2"
        },
        "moves": [
          [
            "e2",
            "e4"
          ],
          [
            "e7",
            "e5"
          ],
          [
            "g1",
            "f3"
          ],
          [
            "b8",
            "c6"
          ],
          [
            "d2",
            "d4"
          ],
          [
            "e5",
            "d4"
          ],
          [
            "f1",
            "c4"
          ],
          [
            "f8",
            "c5"
          ]
        ],
        "comments": [
          "Scotch Game, Haxo Gambit"
        ],
        "marks": {
          "yellow": [
            "f8",
            "c5"
          ]
        }
      },
      "parentId": 854182117,
      "childIds": [],
      "childIdx": -1
    },
    "728638455": {
      "id": 728638455,
      "state": {
        "key": "d8h4",
        "pgn": "Qh4",
        "whitesTurn": true,
        "squares": {
          "a1": "wr1",
          "b1": "wn1",
          "c1": "wb1",
          "d1": "wq1",
          "e1": "wk1",
          "f1": "wb2",
          "h1": "wr2",
          "a2": "wp1",
          "b2": "wp2",
          "c2": "wp3",
          "f2": "wp6",
          "g2": "wp7",
          "h2": "wp8",
          "a7": "bp1",
          "b7": "bp2",
          "c7": "bp3",
          "d7": "bp4",
          "f7": "bp6",
          "g7": "bp7",
          "h7": "bp8",
          "a8": "br1",
          "c8": "bb1",
          "e8": "bk1",
          "f8": "bb2",
          "g8": "bn2",
          "h8": "br2",
          "e4": "wp5",
          "c6": "bn1",
          "d4": "wn2",
          "h4": "bq1"
        },
        "moves": [
          [
            "e2",
            "e4"
          ],
          [
            "e7",
            "e5"
          ],
          [
            "g1",
            "f3"
          ],
          [
            "b8",
            "c6"
          ],
          [
            "d2",
            "d4"
          ],
          [
            "e5",
            "d4"
          ],
          [
            "f3",
            "d4"
          ],
          [
            "d8",
            "h4"
          ]
        ],
        "comments": [
          "Scotch Game, Steinitz Variation"
        ],
        "marks": {
          "yellow": [
            "d8",
            "h4"
          ]
        }
      },
      "parentId": 854184070,
      "childIds": [
        1131625219,
        1131687655
      ],
      "childIdx": 0
    },
    "728667225": {
      "id": 728667225,
      "state": {
        "key": "g8f6",
        "pgn": "Nf6",
        "whitesTurn": true,
        "squares": {
          "a1": "wr1",
          "b1": "wn1",
          "c1": "wb1",
          "d1": "wq1",
          "e1": "wk1",
          "h1": "wr2",
          "a2": "wp1",
          "b2": "wp2",
          "c2": "wp3",
          "f2": "wp6",
          "g2": "wp7",
          "h2": "wp8",
          "a7": "bp1",
          "b7": "bp2",
          "c7": "bp3",
          "d7": "bp4",
          "f7": "bp6",
          "g7": "bp7",
          "h7": "bp8",
          "a8": "br1",
          "c8": "bb1",
          "d8": "bq1",
          "e8": "bk1",
          "f8": "bb2",
          "h8": "br2",
          "e4": "wp5",
          "f3": "wn2",
          "c6": "bn1",
          "d4": "bp5",
          "c4": "wb2",
          "f6": "bn2"
        },
        "moves": [
          [
            "e2",
            "e4"
          ],
          [
            "e7",
            "e5"
          ],
          [
            "g1",
            "f3"
          ],
          [
            "b8",
            "c6"
          ],
          [
            "d2",
            "d4"
          ],
          [
            "e5",
            "d4"
          ],
          [
            "f1",
            "c4"
          ],
          [
            "g8",
            "f6"
          ]
        ],
        "marks": {
          "yellow": [
            "g8",
            "f6"
          ]
        }
      },
      "parentId": 854182117,
      "childIds": [
        1132609409
      ],
      "childIdx": 0
    },
    "728697851": {
      "id": 728697851,
      "state": {
        "key": "f8b4",
        "pgn": "Bb4+",
        "whitesTurn": true,
        "squares": {
          "a1": "wr1",
          "b1": "wn1",
          "c1": "wb1",
          "d1": "wq1",
          "e1": "wk1",
          "f1": "wb2",
          "h1": "wr2",
          "a2": "wp1",
          "b2": "wp2",
          "c2": "wp3",
          "f2": "wp6",
          "g2": "wp7",
          "h2": "wp8",
          "a7": "bp1",
          "b7": "bp2",
          "c7": "bp3",
          "d7": "bp4",
          "f7": "bp6",
          "g7": "bp7",
          "h7": "bp8",
          "a8": "br1",
          "c8": "bb1",
          "d8": "bq1",
          "e8": "bk1",
          "g8": "bn2",
          "h8": "br2",
          "e4": "wp5",
          "c6": "bn1",
          "d4": "wn2",
          "b4": "bb2"
        },
        "moves": [
          [
            "e2",
            "e4"
          ],
          [
            "e7",
            "e5"
          ],
          [
            "g1",
            "f3"
          ],
          [
            "b8",
            "c6"
          ],
          [
            "d2",
            "d4"
          ],
          [
            "e5",
            "d4"
          ],
          [
            "f3",
            "d4"
          ],
          [
            "f8",
            "b4"
          ]
        ],
        "comments": [
          "Scotch Game, Malaniuk Variation"
        ],
        "marks": {
          "yellow": [
            "f8",
            "b4"
          ]
        }
      },
      "parentId": 854184070,
      "childIds": [],
      "childIdx": -1
    },
    "728697883": {
      "id": 728697883,
      "state": {
        "key": "f8c5",
        "pgn": "Bc5",
        "whitesTurn": true,
        "squares": {
          "a1": "wr1",
          "b1": "wn1",
          "c1": "wb1",
          "d1": "wq1",
          "e1": "wk1",
          "f1": "wb2",
          "h1": "wr2",
          "a2": "wp1",
          "b2": "wp2",
          "c2": "wp3",
          "f2": "wp6",
          "g2": "wp7",
          "h2": "wp8",
          "a7": "bp1",
          "b7": "bp2",
          "c7": "bp3",
          "d7": "bp4",
          "f7": "bp6",
          "g7": "bp7",
          "h7": "bp8",
          "a8": "br1",
          "c8": "bb1",
          "d8": "bq1",
          "e8": "bk1",
          "g8": "bn2",
          "h8": "br2",
          "e4": "wp5",
          "c6": "bn1",
          "d4": "wn2",
          "c5": "bb2"
        },
        "moves": [
          [
            "e2",
            "e4"
          ],
          [
            "e7",
            "e5"
          ],
          [
            "g1",
            "f3"
          ],
          [
            "b8",
            "c6"
          ],
          [
            "d2",
            "d4"
          ],
          [
            "e5",
            "d4"
          ],
          [
            "f3",
            "d4"
          ],
          [
            "f8",
            "c5"
          ]
        ],
        "marks": {
          "yellow": [
            "f8",
            "c5"
          ]
        }
      },
      "parentId": 854184070,
      "childIds": [
        1133529921,
        1133529955,
        1133497340
      ],
      "childIdx": 0
    },
    "728727768": {
      "id": 728727768,
      "state": {
        "key": "g8f6",
        "pgn": "Nf6",
        "whitesTurn": true,
        "squares": {
          "a1": "wr1",
          "b1": "wn1",
          "c1": "wb1",
          "d1": "wq1",
          "e1": "wk1",
          "f1": "wb2",
          "h1": "wr2",
          "a2": "wp1",
          "b2": "wp2",
          "c2": "wp3",
          "f2": "wp6",
          "g2": "wp7",
          "h2": "wp8",
          "a7": "bp1",
          "b7": "bp2",
          "c7": "bp3",
          "d7": "bp4",
          "f7": "bp6",
          "g7": "bp7",
          "h7": "bp8",
          "a8": "br1",
          "c8": "bb1",
          "d8": "bq1",
          "e8": "bk1",
          "f8": "bb2",
          "h8": "br2",
          "e4": "wp5",
          "c6": "bn1",
          "d4": "wn2",
          "f6": "bn2"
        },
        "moves": [
          [
            "e2",
            "e4"
          ],
          [
            "e7",
            "e5"
          ],
          [
            "g1",
            "f3"
          ],
          [
            "b8",
            "c6"
          ],
          [
            "d2",
            "d4"
          ],
          [
            "e5",
            "d4"
          ],
          [
            "f3",
            "d4"
          ],
          [
            "g8",
            "f6"
          ]
        ],
        "marks": {
          "yellow": [
            "g8",
            "f6"
          ]
        }
      },
      "parentId": 854184070,
      "childIds": [
        1134456390
      ],
      "childIdx": 0
    },
    "739438882": {
      "id": 739438882,
      "state": {
        "key": "f8b4",
        "pgn": "Bb4",
        "whitesTurn": true,
        "squares": {
          "a1": "wr1",
          "c1": "wb1",
          "d1": "wq1",
          "e1": "wk1",
          "f1": "wb2",
          "h1": "wr2",
          "a2": "wp1",
          "b2": "wp2",
          "c2": "wp3",
          "f2": "wp6",
          "g2": "wp7",
          "h2": "wp8",
          "a7": "bp1",
          "b7": "bp2",
          "c7": "bp3",
          "d7": "bp4",
          "f7": "bp6",
          "g7": "bp7",
          "h7": "bp8",
          "a8": "br1",
          "c8": "bb1",
          "e8": "bk1",
          "g8": "bn2",
          "h8": "br2",
          "e4": "wp5",
          "c6": "bn1",
          "d4": "wn2",
          "h4": "bq1",
          "c3": "wn1",
          "b4": "bb2"
        },
        "moves": [
          [
            "e2",
            "e4"
          ],
          [
            "e7",
            "e5"
          ],
          [
            "g1",
            "f3"
          ],
          [
            "b8",
            "c6"
          ],
          [
            "d2",
            "d4"
          ],
          [
            "e5",
            "d4"
          ],
          [
            "f3",
            "d4"
          ],
          [
            "d8",
            "h4"
          ],
          [
            "b1",
            "c3"
          ],
          [
            "f8",
            "b4"
          ]
        ],
        "comments": [
          "Scotch Game, Modern Defense"
        ],
        "marks": {
          "yellow": [
            "f8",
            "b4"
          ]
        }
      },
      "parentId": 1131625219,
      "childIds": [],
      "childIdx": -1
    },
    "769947005": {
      "id": 769947005,
      "state": {
        "key": "f6g4",
        "pgn": "Ng4",
        "whitesTurn": true,
        "squares": {
          "a1": "wr1",
          "b1": "wn1",
          "c1": "wb1",
          "d1": "wq1",
          "e1": "wk1",
          "h1": "wr2",
          "a2": "wp1",
          "b2": "wp2",
          "c2": "wp3",
          "f2": "wp6",
          "g2": "wp7",
          "h2": "wp8",
          "a7": "bp1",
          "b7": "bp2",
          "c7": "bp3",
          "d7": "bp4",
          "f7": "bp6",
          "g7": "bp7",
          "h7": "bp8",
          "a8": "br1",
          "c8": "bb1",
          "d8": "bq1",
          "e8": "bk1",
          "f8": "bb2",
          "h8": "br2",
          "f3": "wn2",
          "c6": "bn1",
          "d4": "bp5",
          "c4": "wb2",
          "e5": "wp5",
          "g4": "bn2"
        },
        "moves": [
          [
            "e2",
            "e4"
          ],
          [
            "e7",
            "e5"
          ],
          [
            "g1",
            "f3"
          ],
          [
            "b8",
            "c6"
          ],
          [
            "d2",
            "d4"
          ],
          [
            "e5",
            "d4"
          ],
          [
            "f1",
            "c4"
          ],
          [
            "g8",
            "f6"
          ],
          [
            "e4",
            "e5"
          ],
          [
            "f6",
            "g4"
          ]
        ],
        "comments": [
          "Scotch Game, Scotch Gambit, Kingside Variation"
        ],
        "marks": {
          "yellow": [
            "f6",
            "g4"
          ]
        }
      },
      "parentId": 1132609409,
      "childIds": [],
      "childIdx": -1
    },
    "797415177": {
      "id": 797415177,
      "state": {
        "key": "d8f6",
        "pgn": "Qf6",
        "whitesTurn": true,
        "squares": {
          "a1": "wr1",
          "b1": "wn1",
          "d1": "wq1",
          "e1": "wk1",
          "f1": "wb2",
          "h1": "wr2",
          "a2": "wp1",
          "b2": "wp2",
          "c2": "wp3",
          "f2": "wp6",
          "g2": "wp7",
          "h2": "wp8",
          "a7": "bp1",
          "b7": "bp2",
          "c7": "bp3",
          "d7": "bp4",
          "f7": "bp6",
          "g7": "bp7",
          "h7": "bp8",
          "a8": "br1",
          "c8": "bb1",
          "e8": "bk1",
          "g8": "bn2",
          "h8": "br2",
          "e4": "wp5",
          "c6": "bn1",
          "d4": "wn2",
          "c5": "bb2",
          "e3": "wb1",
          "f6": "bq1"
        },
        "moves": [
          [
            "e2",
            "e4"
          ],
          [
            "e7",
            "e5"
          ],
          [
            "g1",
            "f3"
          ],
          [
            "b8",
            "c6"
          ],
          [
            "d2",
            "d4"
          ],
          [
            "e5",
            "d4"
          ],
          [
            "f3",
            "d4"
          ],
          [
            "f8",
            "c5"
          ],
          [
            "c1",
            "e3"
          ],
          [
            "d8",
            "f6"
          ]
        ],
        "marks": {
          "yellow": [
            "d8",
            "f6"
          ]
        }
      },
      "parentId": 1133497340,
      "childIds": [
        1116250706
      ],
      "childIdx": 0
    },
    "798392388": {
      "id": 798392388,
      "state": {
        "key": "c5b4",
        "pgn": "Bb4+",
        "whitesTurn": true,
        "squares": {
          "a1": "wr1",
          "b1": "wn1",
          "c1": "wb1",
          "d1": "wq1",
          "e1": "wk1",
          "f1": "wb2",
          "h1": "wr2",
          "a2": "wp1",
          "b2": "wp2",
          "c2": "wp3",
          "f2": "wp6",
          "g2": "wp7",
          "h2": "wp8",
          "a7": "bp1",
          "b7": "bp2",
          "c7": "bp3",
          "d7": "bp4",
          "f7": "bp6",
          "g7": "bp7",
          "h7": "bp8",
          "a8": "br1",
          "c8": "bb1",
          "d8": "bq1",
          "e8": "bk1",
          "g8": "bn2",
          "h8": "br2",
          "e4": "wp5",
          "c6": "bn1",
          "b3": "wn2",
          "b4": "bb2"
        },
        "moves": [
          [
            "e2",
            "e4"
          ],
          [
            "e7",
            "e5"
          ],
          [
            "g1",
            "f3"
          ],
          [
            "b8",
            "c6"
          ],
          [
            "d2",
            "d4"
          ],
          [
            "e5",
            "d4"
          ],
          [
            "f3",
            "d4"
          ],
          [
            "f8",
            "c5"
          ],
          [
            "d4",
            "b3"
          ],
          [
            "c5",
            "b4"
          ]
        ],
        "comments": [
          "Scotch Game, Romanishin Variation"
        ],
        "marks": {
          "yellow": [
            "c5",
            "b4"
          ]
        }
      },
      "parentId": 1133529921,
      "childIds": [],
      "childIdx": -1
    },
    "798426242": {
      "id": 798426242,
      "state": {
        "key": "d8f6",
        "pgn": "Qf6",
        "whitesTurn": true,
        "squares": {
          "a1": "wr1",
          "b1": "wn1",
          "c1": "wb1",
          "d1": "wq1",
          "e1": "wk1",
          "f1": "wb2",
          "h1": "wr2",
          "a2": "wp1",
          "b2": "wp2",
          "c2": "wp3",
          "f2": "wp6",
          "g2": "wp7",
          "h2": "wp8",
          "a7": "bp1",
          "b7": "bp2",
          "c7": "bp3",
          "d7": "bp4",
          "f7": "bp6",
          "g7": "bp7",
          "h7": "bp8",
          "a8": "br1",
          "c8": "bb1",
          "e8": "bk1",
          "g8": "bn2",
          "h8": "br2",
          "e4": "wp5",
          "c5": "bb2",
          "c6": "wn2",
          "f6": "bq1"
        },
        "moves": [
          [
            "e2",
            "e4"
          ],
          [
            "e7",
            "e5"
          ],
          [
            "g1",
            "f3"
          ],
          [
            "b8",
            "c6"
          ],
          [
            "d2",
            "d4"
          ],
          [
            "e5",
            "d4"
          ],
          [
            "f3",
            "d4"
          ],
          [
            "f8",
            "c5"
          ],
          [
            "d4",
            "c6"
          ],
          [
            "d8",
            "f6"
          ]
        ],
        "comments": [
          "Scotch Game, Classical Variation, Intermezzo Variation"
        ],
        "marks": {
          "yellow": [
            "d8",
            "f6"
          ]
        }
      },
      "parentId": 1133529955,
      "childIds": [],
      "childIdx": -1
    },
    "827085091": {
      "id": 827085091,
      "state": {
        "key": "b7c6",
        "pgn": "bxc6",
        "whitesTurn": true,
        "squares": {
          "a1": "wr1",
          "b1": "wn1",
          "c1": "wb1",
          "d1": "wq1",
          "e1": "wk1",
          "f1": "wb2",
          "h1": "wr2",
          "a2": "wp1",
          "b2": "wp2",
          "c2": "wp3",
          "f2": "wp6",
          "g2": "wp7",
          "h2": "wp8",
          "a7": "bp1",
          "c7": "bp3",
          "d7": "bp4",
          "f7": "bp6",
          "g7": "bp7",
          "h7": "bp8",
          "a8": "br1",
          "c8": "bb1",
          "d8": "bq1",
          "e8": "bk1",
          "f8": "bb2",
          "h8": "br2",
          "e4": "wp5",
          "f6": "bn2",
          "c6": "bp2"
        },
        "moves": [
          [
            "e2",
            "e4"
          ],
          [
            "e7",
            "e5"
          ],
          [
            "g1",
            "f3"
          ],
          [
            "b8",
            "c6"
          ],
          [
            "d2",
            "d4"
          ],
          [
            "e5",
            "d4"
          ],
          [
            "f3",
            "d4"
          ],
          [
            "g8",
            "f6"
          ],
          [
            "d4",
            "c6"
          ],
          [
            "b7",
            "c6"
          ]
        ],
        "marks": {
          "yellow": [
            "b7",
            "c6"
          ]
        }
      },
      "parentId": 1134456390,
      "childIds": [
        2036079608,
        2035987318
      ],
      "childIdx": 0
    },
    "854182117": {
      "id": 854182117,
      "state": {
        "key": "f1c4",
        "pgn": "Bc4",
        "whitesTurn": false,
        "squares": {
          "a1": "wr1",
          "b1": "wn1",
          "c1": "wb1",
          "d1": "wq1",
          "e1": "wk1",
          "h1": "wr2",
          "a2": "wp1",
          "b2": "wp2",
          "c2": "wp3",
          "f2": "wp6",
          "g2": "wp7",
          "h2": "wp8",
          "a7": "bp1",
          "b7": "bp2",
          "c7": "bp3",
          "d7": "bp4",
          "f7": "bp6",
          "g7": "bp7",
          "h7": "bp8",
          "a8": "br1",
          "c8": "bb1",
          "d8": "bq1",
          "e8": "bk1",
          "f8": "bb2",
          "g8": "bn2",
          "h8": "br2",
          "e4": "wp5",
          "f3": "wn2",
          "c6": "bn1",
          "d4": "bp5",
          "c4": "wb2"
        },
        "moves": [
          [
            "e2",
            "e4"
          ],
          [
            "e7",
            "e5"
          ],
          [
            "g1",
            "f3"
          ],
          [
            "b8",
            "c6"
          ],
          [
            "d2",
            "d4"
          ],
          [
            "e5",
            "d4"
          ],
          [
            "f1",
            "c4"
          ]
        ],
        "marks": {
          "yellow": [
            "f1",
            "c4"
          ]
        }
      },
      "parentId": 1828063490,
      "childIds": [
        728667225,
        728637340
      ],
      "childIdx": 0
    },
    "854184070": {
      "id": 854184070,
      "state": {
        "key": "f3d4",
        "pgn": "Nxd4",
        "whitesTurn": false,
        "squares": {
          "a1": "wr1",
          "b1": "wn1",
          "c1": "wb1",
          "d1": "wq1",
          "e1": "wk1",
          "f1": "wb2",
          "h1": "wr2",
          "a2": "wp1",
          "b2": "wp2",
          "c2": "wp3",
          "f2": "wp6",
          "g2": "wp7",
          "h2": "wp8",
          "a7": "bp1",
          "b7": "bp2",
          "c7": "bp3",
          "d7": "bp4",
          "f7": "bp6",
          "g7": "bp7",
          "h7": "bp8",
          "a8": "br1",
          "c8": "bb1",
          "d8": "bq1",
          "e8": "bk1",
          "f8": "bb2",
          "g8": "bn2",
          "h8": "br2",
          "e4": "wp5",
          "c6": "bn1",
          "d4": "wn2"
        },
        "moves": [
          [
            "e2",
            "e4"
          ],
          [
            "e7",
            "e5"
          ],
          [
            "g1",
            "f3"
          ],
          [
            "b8",
            "c6"
          ],
          [
            "d2",
            "d4"
          ],
          [
            "e5",
            "d4"
          ],
          [
            "f3",
            "d4"
          ]
        ],
        "marks": {
          "yellow": [
            "f3",
            "d4"
          ]
        }
      },
      "parentId": 1828063490,
      "childIds": [
        728727768,
        728697883,
        728697851,
        728638455
      ],
      "childIdx": 0
    },
    "1116250706": {
      "id": 1116250706,
      "state": {
        "key": "c2c3",
        "pgn": "c3",
        "whitesTurn": false,
        "squares": {
          "a1": "wr1",
          "b1": "wn1",
          "d1": "wq1",
          "e1": "wk1",
          "f1": "wb2",
          "h1": "wr2",
          "a2": "wp1",
          "b2": "wp2",
          "f2": "wp6",
          "g2": "wp7",
          "h2": "wp8",
          "a7": "bp1",
          "b7": "bp2",
          "c7": "bp3",
          "d7": "bp4",
          "f7": "bp6",
          "g7": "bp7",
          "h7": "bp8",
          "a8": "br1",
          "c8": "bb1",
          "e8": "bk1",
          "g8": "bn2",
          "h8": "br2",
          "e4": "wp5",
          "c6": "bn1",
          "d4": "wn2",
          "c5": "bb2",
          "e3": "wb1",
          "f6": "bq1",
          "c3": "wp3"
        },
        "moves": [
          [
            "e2",
            "e4"
          ],
          [
            "e7",
            "e5"
          ],
          [
            "g1",
            "f3"
          ],
          [
            "b8",
            "c6"
          ],
          [
            "d2",
            "d4"
          ],
          [
            "e5",
            "d4"
          ],
          [
            "f3",
            "d4"
          ],
          [
            "f8",
            "c5"
          ],
          [
            "c1",
            "e3"
          ],
          [
            "d8",
            "f6"
          ],
          [
            "c2",
            "c3"
          ]
        ],
        "marks": {
          "yellow": [
            "c2",
            "c3"
          ]
        }
      },
      "parentId": 797415177,
      "childIds": [
        262827214,
        262858866
      ],
      "childIdx": 0
    },
    "1131625219": {
      "id": 1131625219,
      "state": {
        "key": "b1c3",
        "pgn": "Nc3",
        "whitesTurn": false,
        "squares": {
          "a1": "wr1",
          "c1": "wb1",
          "d1": "wq1",
          "e1": "wk1",
          "f1": "wb2",
          "h1": "wr2",
          "a2": "wp1",
          "b2": "wp2",
          "c2": "wp3",
          "f2": "wp6",
          "g2": "wp7",
          "h2": "wp8",
          "a7": "bp1",
          "b7": "bp2",
          "c7": "bp3",
          "d7": "bp4",
          "f7": "bp6",
          "g7": "bp7",
          "h7": "bp8",
          "a8": "br1",
          "c8": "bb1",
          "e8": "bk1",
          "f8": "bb2",
          "g8": "bn2",
          "h8": "br2",
          "e4": "wp5",
          "c6": "bn1",
          "d4": "wn2",
          "h4": "bq1",
          "c3": "wn1"
        },
        "moves": [
          [
            "e2",
            "e4"
          ],
          [
            "e7",
            "e5"
          ],
          [
            "g1",
            "f3"
          ],
          [
            "b8",
            "c6"
          ],
          [
            "d2",
            "d4"
          ],
          [
            "e5",
            "d4"
          ],
          [
            "f3",
            "d4"
          ],
          [
            "d8",
            "h4"
          ],
          [
            "b1",
            "c3"
          ]
        ],
        "marks": {
          "yellow": [
            "b1",
            "c3"
          ]
        }
      },
      "parentId": 728638455,
      "childIds": [
        739438882
      ],
      "childIdx": 0
    },
    "1131687655": {
      "id": 1131687655,
      "state": {
        "key": "d4b5",
        "pgn": "Nb5",
        "whitesTurn": false,
        "squares": {
          "a1": "wr1",
          "b1": "wn1",
          "c1": "wb1",
          "d1": "wq1",
          "e1": "wk1",
          "f1": "wb2",
          "h1": "wr2",
          "a2": "wp1",
          "b2": "wp2",
          "c2": "wp3",
          "f2": "wp6",
          "g2": "wp7",
          "h2": "wp8",
          "a7": "bp1",
          "b7": "bp2",
          "c7": "bp3",
          "d7": "bp4",
          "f7": "bp6",
          "g7": "bp7",
          "h7": "bp8",
          "a8": "br1",
          "c8": "bb1",
          "e8": "bk1",
          "f8": "bb2",
          "g8": "bn2",
          "h8": "br2",
          "e4": "wp5",
          "c6": "bn1",
          "h4": "bq1",
          "b5": "wn2"
        },
        "moves": [
          [
            "e2",
            "e4"
          ],
          [
            "e7",
            "e5"
          ],
          [
            "g1",
            "f3"
          ],
          [
            "b8",
            "c6"
          ],
          [
            "d2",
            "d4"
          ],
          [
            "e5",
            "d4"
          ],
          [
            "f3",
            "d4"
          ],
          [
            "d8",
            "h4"
          ],
          [
            "d4",
            "b5"
          ]
        ],
        "comments": [
          "Scotch Game, Horwitz Attack"
        ],
        "marks": {
          "yellow": [
            "d4",
            "b5"
          ]
        }
      },
      "parentId": 728638455,
      "childIds": [],
      "childIdx": -1
    },
    "1132609409": {
      "id": 1132609409,
      "state": {
        "key": "e4e5",
        "pgn": "e5",
        "whitesTurn": false,
        "squares": {
          "a1": "wr1",
          "b1": "wn1",
          "c1": "wb1",
          "d1": "wq1",
          "e1": "wk1",
          "h1": "wr2",
          "a2": "wp1",
          "b2": "wp2",
          "c2": "wp3",
          "f2": "wp6",
          "g2": "wp7",
          "h2": "wp8",
          "a7": "bp1",
          "b7": "bp2",
          "c7": "bp3",
          "d7": "bp4",
          "f7": "bp6",
          "g7": "bp7",
          "h7": "bp8",
          "a8": "br1",
          "c8": "bb1",
          "d8": "bq1",
          "e8": "bk1",
          "f8": "bb2",
          "h8": "br2",
          "f3": "wn2",
          "c6": "bn1",
          "d4": "bp5",
          "c4": "wb2",
          "f6": "bn2",
          "e5": "wp5"
        },
        "moves": [
          [
            "e2",
            "e4"
          ],
          [
            "e7",
            "e5"
          ],
          [
            "g1",
            "f3"
          ],
          [
            "b8",
            "c6"
          ],
          [
            "d2",
            "d4"
          ],
          [
            "e5",
            "d4"
          ],
          [
            "f1",
            "c4"
          ],
          [
            "g8",
            "f6"
          ],
          [
            "e4",
            "e5"
          ]
        ],
        "marks": {
          "yellow": [
            "e4",
            "e5"
          ]
        }
      },
      "parentId": 728667225,
      "childIds": [
        769947005
      ],
      "childIdx": 0
    },
    "1133497340": {
      "id": 1133497340,
      "state": {
        "key": "c1e3",
        "pgn": "Be3",
        "whitesTurn": false,
        "squares": {
          "a1": "wr1",
          "b1": "wn1",
          "d1": "wq1",
          "e1": "wk1",
          "f1": "wb2",
          "h1": "wr2",
          "a2": "wp1",
          "b2": "wp2",
          "c2": "wp3",
          "f2": "wp6",
          "g2": "wp7",
          "h2": "wp8",
          "a7": "bp1",
          "b7": "bp2",
          "c7": "bp3",
          "d7": "bp4",
          "f7": "bp6",
          "g7": "bp7",
          "h7": "bp8",
          "a8": "br1",
          "c8": "bb1",
          "d8": "bq1",
          "e8": "bk1",
          "g8": "bn2",
          "h8": "br2",
          "e4": "wp5",
          "c6": "bn1",
          "d4": "wn2",
          "c5": "bb2",
          "e3": "wb1"
        },
        "moves": [
          [
            "e2",
            "e4"
          ],
          [
            "e7",
            "e5"
          ],
          [
            "g1",
            "f3"
          ],
          [
            "b8",
            "c6"
          ],
          [
            "d2",
            "d4"
          ],
          [
            "e5",
            "d4"
          ],
          [
            "f3",
            "d4"
          ],
          [
            "f8",
            "c5"
          ],
          [
            "c1",
            "e3"
          ]
        ],
        "marks": {
          "yellow": [
            "c1",
            "e3"
          ]
        }
      },
      "parentId": 728697883,
      "childIds": [
        797415177
      ],
      "childIdx": 0
    },
    "1133529921": {
      "id": 1133529921,
      "state": {
        "key": "d4b3",
        "pgn": "Nb3",
        "whitesTurn": false,
        "squares": {
          "a1": "wr1",
          "b1": "wn1",
          "c1": "wb1",
          "d1": "wq1",
          "e1": "wk1",
          "f1": "wb2",
          "h1": "wr2",
          "a2": "wp1",
          "b2": "wp2",
          "c2": "wp3",
          "f2": "wp6",
          "g2": "wp7",
          "h2": "wp8",
          "a7": "bp1",
          "b7": "bp2",
          "c7": "bp3",
          "d7": "bp4",
          "f7": "bp6",
          "g7": "bp7",
          "h7": "bp8",
          "a8": "br1",
          "c8": "bb1",
          "d8": "bq1",
          "e8": "bk1",
          "g8": "bn2",
          "h8": "br2",
          "e4": "wp5",
          "c6": "bn1",
          "c5": "bb2",
          "b3": "wn2"
        },
        "moves": [
          [
            "e2",
            "e4"
          ],
          [
            "e7",
            "e5"
          ],
          [
            "g1",
            "f3"
          ],
          [
            "b8",
            "c6"
          ],
          [
            "d2",
            "d4"
          ],
          [
            "e5",
            "d4"
          ],
          [
            "f3",
            "d4"
          ],
          [
            "f8",
            "c5"
          ],
          [
            "d4",
            "b3"
          ]
        ],
        "marks": {
          "yellow": [
            "d4",
            "b3"
          ]
        }
      },
      "parentId": 728697883,
      "childIds": [
        798392388
      ],
      "childIdx": 0
    },
    "1133529955": {
      "id": 1133529955,
      "state": {
        "key": "d4c6",
        "pgn": "Nxc6",
        "whitesTurn": false,
        "squares": {
          "a1": "wr1",
          "b1": "wn1",
          "c1": "wb1",
          "d1": "wq1",
          "e1": "wk1",
          "f1": "wb2",
          "h1": "wr2",
          "a2": "wp1",
          "b2": "wp2",
          "c2": "wp3",
          "f2": "wp6",
          "g2": "wp7",
          "h2": "wp8",
          "a7": "bp1",
          "b7": "bp2",
          "c7": "bp3",
          "d7": "bp4",
          "f7": "bp6",
          "g7": "bp7",
          "h7": "bp8",
          "a8": "br1",
          "c8": "bb1",
          "d8": "bq1",
          "e8": "bk1",
          "g8": "bn2",
          "h8": "br2",
          "e4": "wp5",
          "c5": "bb2",
          "c6": "wn2"
        },
        "moves": [
          [
            "e2",
            "e4"
          ],
          [
            "e7",
            "e5"
          ],
          [
            "g1",
            "f3"
          ],
          [
            "b8",
            "c6"
          ],
          [
            "d2",
            "d4"
          ],
          [
            "e5",
            "d4"
          ],
          [
            "f3",
            "d4"
          ],
          [
            "f8",
            "c5"
          ],
          [
            "d4",
            "c6"
          ]
        ],
        "marks": {
          "yellow": [
            "d4",
            "c6"
          ]
        }
      },
      "parentId": 728697883,
      "childIds": [
        798426242
      ],
      "childIdx": 0
    },
    "1134456390": {
      "id": 1134456390,
      "state": {
        "key": "d4c6",
        "pgn": "Nxc6",
        "whitesTurn": false,
        "squares": {
          "a1": "wr1",
          "b1": "wn1",
          "c1": "wb1",
          "d1": "wq1",
          "e1": "wk1",
          "f1": "wb2",
          "h1": "wr2",
          "a2": "wp1",
          "b2": "wp2",
          "c2": "wp3",
          "f2": "wp6",
          "g2": "wp7",
          "h2": "wp8",
          "a7": "bp1",
          "b7": "bp2",
          "c7": "bp3",
          "d7": "bp4",
          "f7": "bp6",
          "g7": "bp7",
          "h7": "bp8",
          "a8": "br1",
          "c8": "bb1",
          "d8": "bq1",
          "e8": "bk1",
          "f8": "bb2",
          "h8": "br2",
          "e4": "wp5",
          "f6": "bn2",
          "c6": "wn2"
        },
        "moves": [
          [
            "e2",
            "e4"
          ],
          [
            "e7",
            "e5"
          ],
          [
            "g1",
            "f3"
          ],
          [
            "b8",
            "c6"
          ],
          [
            "d2",
            "d4"
          ],
          [
            "e5",
            "d4"
          ],
          [
            "f3",
            "d4"
          ],
          [
            "g8",
            "f6"
          ],
          [
            "d4",
            "c6"
          ]
        ],
        "marks": {
          "yellow": [
            "d4",
            "c6"
          ]
        }
      },
      "parentId": 728727768,
      "childIds": [
        827085091
      ],
      "childIdx": 0
    },
    "1156584507": {
      "id": 1156584507,
      "state": {
        "key": "b8c6",
        "pgn": "Nc6",
        "whitesTurn": true,
        "squares": {
          "a1": "wr1",
          "b1": "wn1",
          "c1": "wb1",
          "d1": "wq1",
          "e1": "wk1",
          "f1": "wb2",
          "h1": "wr2",
          "a2": "wp1",
          "b2": "wp2",
          "c2": "wp3",
          "d2": "wp4",
          "f2": "wp6",
          "g2": "wp7",
          "h2": "wp8",
          "a7": "bp1",
          "b7": "bp2",
          "c7": "bp3",
          "d7": "bp4",
          "f7": "bp6",
          "g7": "bp7",
          "h7": "bp8",
          "a8": "br1",
          "c8": "bb1",
          "d8": "bq1",
          "e8": "bk1",
          "f8": "bb2",
          "g8": "bn2",
          "h8": "br2",
          "e4": "wp5",
          "e5": "bp5",
          "f3": "wn2",
          "c6": "bn1"
        },
        "moves": [
          [
            "e2",
            "e4"
          ],
          [
            "e7",
            "e5"
          ],
          [
            "g1",
            "f3"
          ],
          [
            "b8",
            "c6"
          ]
        ],
        "marks": {
          "yellow": [
            "b8",
            "c6"
          ]
        }
      },
      "parentId": 244527714,
      "childIds": [
        1513111524
      ],
      "childIdx": 0
    },
    "1513111524": {
      "id": 1513111524,
      "state": {
        "key": "d2d4",
        "pgn": "d4",
        "whitesTurn": false,
        "squares": {
          "a1": "wr1",
          "b1": "wn1",
          "c1": "wb1",
          "d1": "wq1",
          "e1": "wk1",
          "f1": "wb2",
          "h1": "wr2",
          "a2": "wp1",
          "b2": "wp2",
          "c2": "wp3",
          "f2": "wp6",
          "g2": "wp7",
          "h2": "wp8",
          "a7": "bp1",
          "b7": "bp2",
          "c7": "bp3",
          "d7": "bp4",
          "f7": "bp6",
          "g7": "bp7",
          "h7": "bp8",
          "a8": "br1",
          "c8": "bb1",
          "d8": "bq1",
          "e8": "bk1",
          "f8": "bb2",
          "g8": "bn2",
          "h8": "br2",
          "e4": "wp5",
          "e5": "bp5",
          "f3": "wn2",
          "c6": "bn1",
          "d4": "wp4"
        },
        "moves": [
          [
            "e2",
            "e4"
          ],
          [
            "e7",
            "e5"
          ],
          [
            "g1",
            "f3"
          ],
          [
            "b8",
            "c6"
          ],
          [
            "d2",
            "d4"
          ]
        ],
        "marks": {
          "yellow": [
            "d2",
            "d4"
          ]
        }
      },
      "parentId": 1156584507,
      "childIds": [
        1828063490
      ],
      "childIdx": 0
    },
    "1724903101": {
      "id": 1724903101,
      "state": {
        "key": "d1d2",
        "pgn": "Qd2",
        "whitesTurn": false,
        "squares": {
          "a1": "wr1",
          "b1": "wn1",
          "e1": "wk1",
          "f1": "wb2",
          "h1": "wr2",
          "a2": "wp1",
          "b2": "wp2",
          "f2": "wp6",
          "g2": "wp7",
          "h2": "wp8",
          "a7": "bp1",
          "b7": "bp2",
          "c7": "bp3",
          "d7": "bp4",
          "f7": "bp6",
          "g7": "bp7",
          "h7": "bp8",
          "a8": "br1",
          "c8": "bb1",
          "e8": "bk1",
          "h8": "br2",
          "e4": "wp5",
          "c6": "bn1",
          "d4": "wn2",
          "c5": "bb2",
          "e3": "wb1",
          "f6": "bq1",
          "c3": "wp3",
          "e7": "bn2",
          "d2": "wq1"
        },
        "moves": [
          [
            "e2",
            "e4"
          ],
          [
            "e7",
            "e5"
          ],
          [
            "g1",
            "f3"
          ],
          [
            "b8",
            "c6"
          ],
          [
            "d2",
            "d4"
          ],
          [
            "e5",
            "d4"
          ],
          [
            "f3",
            "d4"
          ],
          [
            "f8",
            "c5"
          ],
          [
            "c1",
            "e3"
          ],
          [
            "d8",
            "f6"
          ],
          [
            "c2",
            "c3"
          ],
          [
            "g8",
            "e7"
          ],
          [
            "d1",
            "d2"
          ]
        ],
        "comments": [
          "Scotch Game, Classical Variation, Blackburne Attack"
        ],
        "marks": {
          "yellow": [
            "d1",
            "d2"
          ]
        }
      },
      "parentId": 262858866,
      "childIds": [],
      "childIdx": -1
    },
    "1724905953": {
      "id": 1724905953,
      "state": {
        "key": "d4c2",
        "pgn": "Nc2",
        "whitesTurn": false,
        "squares": {
          "a1": "wr1",
          "b1": "wn1",
          "d1": "wq1",
          "e1": "wk1",
          "f1": "wb2",
          "h1": "wr2",
          "a2": "wp1",
          "b2": "wp2",
          "f2": "wp6",
          "g2": "wp7",
          "h2": "wp8",
          "a7": "bp1",
          "b7": "bp2",
          "c7": "bp3",
          "d7": "bp4",
          "f7": "bp6",
          "g7": "bp7",
          "h7": "bp8",
          "a8": "br1",
          "c8": "bb1",
          "e8": "bk1",
          "h8": "br2",
          "e4": "wp5",
          "c6": "bn1",
          "c5": "bb2",
          "e3": "wb1",
          "f6": "bq1",
          "c3": "wp3",
          "e7": "bn2",
          "c2": "wn2"
        },
        "moves": [
          [
            "e2",
            "e4"
          ],
          [
            "e7",
            "e5"
          ],
          [
            "g1",
            "f3"
          ],
          [
            "b8",
            "c6"
          ],
          [
            "d2",
            "d4"
          ],
          [
            "e5",
            "d4"
          ],
          [
            "f3",
            "d4"
          ],
          [
            "f8",
            "c5"
          ],
          [
            "c1",
            "e3"
          ],
          [
            "d8",
            "f6"
          ],
          [
            "c2",
            "c3"
          ],
          [
            "g8",
            "e7"
          ],
          [
            "d4",
            "c2"
          ]
        ],
        "comments": [
          "Scotch Game, Meitner Variation"
        ],
        "marks": {
          "yellow": [
            "d4",
            "c2"
          ]
        }
      },
      "parentId": 262858866,
      "childIds": [],
      "childIdx": -1
    },
    "1828063490": {
      "id": 1828063490,
      "state": {
        "key": "e5d4",
        "pgn": "exd4",
        "whitesTurn": true,
        "squares": {
          "a1": "wr1",
          "b1": "wn1",
          "c1": "wb1",
          "d1": "wq1",
          "e1": "wk1",
          "f1": "wb2",
          "h1": "wr2",
          "a2": "wp1",
          "b2": "wp2",
          "c2": "wp3",
          "f2": "wp6",
          "g2": "wp7",
          "h2": "wp8",
          "a7": "bp1",
          "b7": "bp2",
          "c7": "bp3",
          "d7": "bp4",
          "f7": "bp6",
          "g7": "bp7",
          "h7": "bp8",
          "a8": "br1",
          "c8": "bb1",
          "d8": "bq1",
          "e8": "bk1",
          "f8": "bb2",
          "g8": "bn2",
          "h8": "br2",
          "e4": "wp5",
          "f3": "wn2",
          "c6": "bn1",
          "d4": "bp5"
        },
        "moves": [
          [
            "e2",
            "e4"
          ],
          [
            "e7",
            "e5"
          ],
          [
            "g1",
            "f3"
          ],
          [
            "b8",
            "c6"
          ],
          [
            "d2",
            "d4"
          ],
          [
            "e5",
            "d4"
          ]
        ],
        "marks": {
          "yellow": [
            "e5",
            "d4"
          ]
        }
      },
      "parentId": 1513111524,
      "childIds": [
        854184070,
        854182117
      ],
      "childIdx": 0
    },
    "1877669921": {
      "id": 1877669921,
      "state": {
        "key": "e7e5",
        "pgn": "e5",
        "whitesTurn": true,
        "squares": {
          "a1": "wr1",
          "b1": "wn1",
          "c1": "wb1",
          "d1": "wq1",
          "e1": "wk1",
          "f1": "wb2",
          "g1": "wn2",
          "h1": "wr2",
          "a2": "wp1",
          "b2": "wp2",
          "c2": "wp3",
          "d2": "wp4",
          "f2": "wp6",
          "g2": "wp7",
          "h2": "wp8",
          "a7": "bp1",
          "b7": "bp2",
          "c7": "bp3",
          "d7": "bp4",
          "f7": "bp6",
          "g7": "bp7",
          "h7": "bp8",
          "a8": "br1",
          "b8": "bn1",
          "c8": "bb1",
          "d8": "bq1",
          "e8": "bk1",
          "f8": "bb2",
          "g8": "bn2",
          "h8": "br2",
          "e4": "wp5",
          "e5": "bp5"
        },
        "moves": [
          [
            "e2",
            "e4"
          ],
          [
            "e7",
            "e5"
          ]
        ],
        "marks": {
          "yellow": [
            "e7",
            "e5"
          ]
        }
      },
      "parentId": 614154010,
      "childIds": [
        244527714
      ],
      "childIdx": 0
    },
    "2035987318": {
      "id": 2035987318,
      "state": {
        "key": "b1d2",
        "pgn": "Nd2",
        "whitesTurn": false,
        "squares": {
          "a1": "wr1",
          "c1": "wb1",
          "d1": "wq1",
          "e1": "wk1",
          "f1": "wb2",
          "h1": "wr2",
          "a2": "wp1",
          "b2": "wp2",
          "c2": "wp3",
          "f2": "wp6",
          "g2": "wp7",
          "h2": "wp8",
          "a7": "bp1",
          "c7": "bp3",
          "d7": "bp4",
          "f7": "bp6",
          "g7": "bp7",
          "h7": "bp8",
          "a8": "br1",
          "c8": "bb1",
          "d8": "bq1",
          "e8": "bk1",
          "f8": "bb2",
          "h8": "br2",
          "e4": "wp5",
          "f6": "bn2",
          "c6": "bp2",
          "d2": "wn1"
        },
        "moves": [
          [
            "e2",
            "e4"
          ],
          [
            "e7",
            "e5"
          ],
          [
            "g1",
            "f3"
          ],
          [
            "b8",
            "c6"
          ],
          [
            "d2",
            "d4"
          ],
          [
            "e5",
            "d4"
          ],
          [
            "f3",
            "d4"
          ],
          [
            "g8",
            "f6"
          ],
          [
            "d4",
            "c6"
          ],
          [
            "b7",
            "c6"
          ],
          [
            "b1",
            "d2"
          ]
        ],
        "comments": [
          "Scotch Game, Tartakower Variation"
        ],
        "marks": {
          "yellow": [
            "b1",
            "d2"
          ]
        }
      },
      "parentId": 827085091,
      "childIds": [],
      "childIdx": -1
    },
    "2036079608": {
      "id": 2036079608,
      "state": {
        "key": "e4e5",
        "pgn": "e5",
        "whitesTurn": false,
        "squares": {
          "a1": "wr1",
          "b1": "wn1",
          "c1": "wb1",
          "d1": "wq1",
          "e1": "wk1",
          "f1": "wb2",
          "h1": "wr2",
          "a2": "wp1",
          "b2": "wp2",
          "c2": "wp3",
          "f2": "wp6",
          "g2": "wp7",
          "h2": "wp8",
          "a7": "bp1",
          "c7": "bp3",
          "d7": "bp4",
          "f7": "bp6",
          "g7": "bp7",
          "h7": "bp8",
          "a8": "br1",
          "c8": "bb1",
          "d8": "bq1",
          "e8": "bk1",
          "f8": "bb2",
          "h8": "br2",
          "f6": "bn2",
          "c6": "bp2",
          "e5": "wp5"
        },
        "moves": [
          [
            "e2",
            "e4"
          ],
          [
            "e7",
            "e5"
          ],
          [
            "g1",
            "f3"
          ],
          [
            "b8",
            "c6"
          ],
          [
            "d2",
            "d4"
          ],
          [
            "e5",
            "d4"
          ],
          [
            "f3",
            "d4"
          ],
          [
            "g8",
            "f6"
          ],
          [
            "d4",
            "c6"
          ],
          [
            "b7",
            "c6"
          ],
          [
            "e4",
            "e5"
          ]
        ],
        "comments": [
          "Scotch Game, Mieses Variation"
        ],
        "marks": {
          "yellow": [
            "e4",
            "e5"
          ]
        }
      },
      "parentId": 827085091,
      "childIds": [],
      "childIdx": -1
    }
  }
}